pink.py
pink-0.8.1.dist-info/METADATA
pink-0.8.1.dist-info/RECORD
pink-0.8.1.dist-info/WHEEL
pink-0.8.1.dist-info/entry_points.txt
pink-0.8.1.dist-info/top_level.txt
