Metadata-Version: 2.1
Name: pink
Version: 0.8.1
Summary: Reformatted code via the command line.
Home-page: https://github.com/chenjiandongx/pink
Author: chenjiandongx
Author-email: chenjiandongx@qq.com
License: MIT
Platform: UNKNOWN
Requires-Dist: black
Requires-Dist: glob2
Requires-Dist: isort
Requires-Dist: delegator.py
